eth_wallet_generater-0.1.0.data/scripts/generateAddress.py
eth_wallet_generater-0.1.0.data/scripts/main.py
src/__init__.py
src/addressManager.py
src/generateAddress.py
src/main.py
src/option.py
src/output.py
eth_wallet_generater-0.1.0.dist-info/LICENCE.txt
eth_wallet_generater-0.1.0.dist-info/METADATA
eth_wallet_generater-0.1.0.dist-info/WHEEL
eth_wallet_generater-0.1.0.dist-info/entry_points.txt
eth_wallet_generater-0.1.0.dist-info/top_level.txt
eth_wallet_generater-0.1.0.dist-info/RECORD
