Metadata-Version: 2.1
Name: eth-wallet-generater
Version: 0.1.0
Summary: this is Ethereum wallet generater.
Home-page: UNKNOWN
Author: sinsinpurin
License: MIT
Platform: UNKNOWN
Requires-Python: >=3.7
Requires-Dist: pysha3 (==1.0.2)
Requires-Dist: coincurve (==13.0.0)
Requires-Dist: inquirer (==2.7.0)
Requires-Dist: wheel (==0.34.2)
Requires-Dist: pyfiglet (==0.8.post1)
Requires-Dist: openpyxl (==3.0.3)
